mlprotection/__init__.py
mlprotection/main.py
mlprotection-0.1.5.dist-info/METADATA
mlprotection-0.1.5.dist-info/WHEEL
mlprotection-0.1.5.dist-info/top_level.txt
mlprotection-0.1.5.dist-info/RECORD
