Metadata-Version: 2.4
Name: mlprotection
Version: 0.1.5
Summary: Библиотека для обнаружения аномалий и потенциально "отравленных" данных в датасетах
Home-page: https://github.com/ivblz/mlprotection
Author: ivblz
Project-URL: Documentation, https://github.com/ivblz/mlprotection
Requires-Python: >=3.6
Requires-Dist: pandas>=1.3.0
Requires-Dist: numpy>=1.20.0
Requires-Dist: scikit-learn>=1.0.0
Requires-Dist: matplotlib>=3.4.0
Requires-Dist: seaborn>=0.11.0
Dynamic: author
Dynamic: description
Dynamic: description-content-type
Dynamic: home-page
Dynamic: project-url
Dynamic: requires-dist
Dynamic: requires-python
Dynamic: summary
